uMQ/__init__.py
uMQ/uMQ.py
uMQ-1.0.2.dist-info/LICENSE
uMQ-1.0.2.dist-info/METADATA
uMQ-1.0.2.dist-info/WHEEL
uMQ-1.0.2.dist-info/top_level.txt
uMQ-1.0.2.dist-info/RECORD
