Metadata-Version: 2.1
Name: uMQ
Version: 1.0.2
Summary: A minimal and reliable JSON MQ library!
Home-page: https://github.com/aroshanineshat/uMQ
Author: Arash Roshanineshat
Author-email: aroshanineshat@email.arizona.edu
License: UNKNOWN
Project-URL: Bug Tracker, https://github.com/aroshanineshat/uMQ/issues
Platform: UNKNOWN
Classifier: Programming Language :: Python :: 3
Classifier: License :: OSI Approved :: MIT License
Classifier: Operating System :: OS Independent
Requires-Python: >=3.6
License-File: LICENSE
